obserware/__init__.py
obserware/appdata/org.t0xic0der.obserware.desktop
obserware/appdata/org.t0xic0der.obserware.metainfo.xml
obserware/appdata/org.t0xic0der.obserware.png
obserware/main.py
obserware/sources/__init__.py
obserware/sources/commons/__init__.py
obserware/sources/commons/resources.py
obserware/sources/readers/__init__.py
obserware/sources/readers/mainwind/__init__.py
obserware/sources/readers/mainwind/tab_information.py
obserware/sources/readers/mainwind/tab_network.py
obserware/sources/readers/mainwind/tab_partitions.py
obserware/sources/readers/mainwind/tab_performance.py
obserware/sources/readers/mainwind/tab_processes.py
obserware/sources/readers/mainwind/tab_resources.py
obserware/sources/readers/procwind/__init__.py
obserware/sources/readers/procwind/controller.py
obserware/sources/readers/procwind/provider.py
obserware/sources/screens/__init__.py
obserware/sources/screens/mainwind/__init__.py
obserware/sources/screens/mainwind/interface.py
obserware/sources/screens/mainwind/operations.py
obserware/sources/screens/mainwind/worker.py
obserware/sources/screens/procwind/__init__.py
obserware/sources/screens/procwind/interface.py
obserware/sources/screens/procwind/operations.py
obserware/sources/widgets/__init__.py
obserware/sources/widgets/lgptwdgt/__init__.py
obserware/sources/widgets/lgptwdgt/interface.py
obserware/sources/widgets/lgptwdgt/operations.py
obserware/sources/widgets/ntwkwdgt/__init__.py
obserware/sources/widgets/ntwkwdgt/interface.py
obserware/sources/widgets/ntwkwdgt/operations.py
obserware/sources/widgets/perfwdgt/__init__.py
obserware/sources/widgets/perfwdgt/interface.py
obserware/sources/widgets/perfwdgt/operations.py
obserware/sources/widgets/phptwdgt/__init__.py
obserware/sources/widgets/phptwdgt/interface.py
obserware/sources/widgets/phptwdgt/operations.py
obserware-0.2.9.dist-info/entry_points.txt
obserware-0.2.9.dist-info/LICENSE
obserware-0.2.9.dist-info/WHEEL
obserware-0.2.9.dist-info/METADATA
obserware-0.2.9.dist-info/RECORD
