Metadata-Version: 2.1
Name: obserware
Version: 0.2.9
Summary: An advanced system monitor utility written in Python and Qt
Home-page: https://gitlab.com/t0xic0der/obserware
License: GPL-3.0-or-later
Keywords: qt,monitoring,performance,linux,observation
Author: Akashdeep Dhar
Author-email: akashdeep.dhar@gmail.com
Maintainer: Akashdeep Dhar
Maintainer-email: akashdeep.dhar@gmail.com
Requires-Python: >=3.8,<4.0
Classifier: Development Status :: 4 - Beta
Classifier: Environment :: X11 Applications
Classifier: Intended Audience :: End Users/Desktop
Classifier: License :: OSI Approved :: GNU General Public License v3 or later (GPLv3+)
Classifier: Natural Language :: English
Classifier: Operating System :: POSIX :: Linux
Classifier: Programming Language :: Python :: 3
Classifier: Programming Language :: Python :: 3.10
Classifier: Programming Language :: Python :: 3.11
Classifier: Programming Language :: Python :: 3.8
Classifier: Programming Language :: Python :: 3.9
Classifier: Topic :: System :: Monitoring
Classifier: Topic :: System :: Operating System
Classifier: Topic :: Utilities
Requires-Dist: distro (>=1.6.0,<2.0.0)
Requires-Dist: psutil (>=5.8.0,<6.0.0)
Requires-Dist: py-cpuinfo (>=8.0.0,<9.0.0)
Requires-Dist: pyqt5 (>=5.15.6,<6.0.0)
Requires-Dist: pyqtchart (>=5.15.2,<6.0.0)
Project-URL: Documentation, https://gitlab.com/t0xic0der/obserware/-/blob/main/README.md
Project-URL: Repository, https://gitlab.com/t0xic0der/obserware
